setup.py
reverse_sort/__init__.py
reverse_sort/sort_functions.py
reverse_sort.egg-info/PKG-INFO
reverse_sort.egg-info/SOURCES.txt
reverse_sort.egg-info/dependency_links.txt
reverse_sort.egg-info/not-zip-safe
reverse_sort.egg-info/pbr.json
reverse_sort.egg-info/top_level.txt