Metadata-Version: 1.0
Name: reverse-sort
Version: 0.1
Summary: Reverse sort a given python list.
Home-page: https://github.com/shashankdixena/reverse_sort
Author: Shashank Dixena
Author-email: shashankdixena7793@gmail.com
License: MIT
Platform: UNKNOWN
